kepler_apertures/EXBAMachine.py
kepler_apertures/KeplerFFI.py
kepler_apertures/KeplerPRF.py
kepler_apertures/__init__.py
kepler_apertures/data/exba_tpfs_info.csv
kepler_apertures/data/ffi_prf_models_v0.1.0.csv
kepler_apertures/data/ffi_prf_models_v0.1.0.fits
kepler_apertures/utils.py
kepler_apertures/version.py
kepler_apertures-0.1.0.dist-info/LICENSE
kepler_apertures-0.1.0.dist-info/WHEEL
kepler_apertures-0.1.0.dist-info/METADATA
kepler_apertures-0.1.0.dist-info/RECORD
