Metadata-Version: 2.1
Name: kepler-apertures
Version: 0.1.0
Summary: Tools to compute PRF models from Kepler's FFI and use them to do aperture photometry and compile light curves of the EXBA masks. 
Home-page: https://github.com/jorgemarpa/kepler-apertures
License: MIT
Keywords: NASA, Kepler, Astronomy
Author: Jorge Martinez-Palomera
Author-email: jorgemarpa@ug.uchile.cl
Requires-Python: >=3.8,<4.0
Classifier: Intended Audience :: Science/Research
Classifier: License :: OSI Approved :: MIT License
Classifier: Programming Language :: Python :: 3
Classifier: Programming Language :: Python :: 3.8
Classifier: Programming Language :: Python :: 3.9
Classifier: Topic :: Scientific/Engineering :: Astronomy
Requires-Dist: astropy (>=4.2,<5.0)
Requires-Dist: lightkurve (>=2.0.4,<3.0.0)
Requires-Dist: matplotlib (>=3.3.4,<4.0.0)
Requires-Dist: numpy (>=1.19.4,<2.0.0)
Requires-Dist: pandas (>=1.2.0,<1.3.0)
Requires-Dist: patsy (>=0.5.1,<0.6.0)
Requires-Dist: photutils (>=1.0.2,<2.0.0)
Requires-Dist: pyia (>=1.2,<2.0)
Requires-Dist: scipy (>=1.6.1,<2.0.0)
Requires-Dist: tqdm (>=4.59.0,<5.0.0)
Requires-Dist: wget (>=3.0,<4.0)
Project-URL: Repository, https://github.com/jorgemarpa/kepler-apertures
